fern/__init__.py
fern/applications.py
fern/logging.py
fern/losses.py
fern/metrics.py
fern/pipeline.py
fern/train.py
fern/data/__init__.py
fern/data/data_balance.py
fern/data/data_class.py
fern/data/data_clean.py
fern/data/data_download.py
fern/data/data_split.py
fern/data/data_tokenize.py
fern/data/data_utils.py
fern/models/__init__.py
fern/models/layers.py
fern/models/model.py
fern/utils/__init__.py
fern/utils/common.py
fern/utils/tensor_ops.py
Fern2-1.4.1.dist-info/LICENSE
Fern2-1.4.1.dist-info/METADATA
Fern2-1.4.1.dist-info/WHEEL
Fern2-1.4.1.dist-info/top_level.txt
Fern2-1.4.1.dist-info/RECORD
